deepstrike/__init__.py
deepstrike/__main__.py
deepstrike/cli.py
deepstrike/config.py
deepstrike/tor.py
deepstrike/ai/__init__.py
deepstrike/ai/multi_agent.py
deepstrike/ai/providers.py
deepstrike/modules/crypto_recovery.py
deepstrike/modules/darkweb_scraper.py
deepstrike/ui/cli.py
deepstrike/ui/doctor.py
deepstrike/ui/menu.py
deepstrike_ai-2.2.1.dist-info/METADATA
deepstrike_ai-2.2.1.dist-info/WHEEL
deepstrike_ai-2.2.1.dist-info/entry_points.txt
deepstrike_ai-2.2.1.dist-info/top_level.txt
deepstrike_ai-2.2.1.dist-info/RECORD
