Metadata-Version: 2.4
Name: deepstrike-ai
Version: 2.2.1
Summary: AI-assisted cybersecurity research & authorized penetration-testing framework
Home-page: https://github.com/yourusername/deepstrike-ai
Author: DeepStrike Team
Author-email: DeepStrike Team <hackura@keemail.me>
Maintainer-email: DeepStrike Team <hackura@keemail.me>
Project-URL: Homepage, https://github.com/hackura/deepstrike-ai
Project-URL: Repository, https://github.com/hackura/deepstrike-ai.git
Project-URL: Issues, https://github.com/hackura/deepstrike-ai/issues
Keywords: cybersecurity,security-testing,penetration-testing,ai,research,privacy
Classifier: Development Status :: 4 - Beta
Classifier: Intended Audience :: Information Technology
Classifier: Intended Audience :: Education
Classifier: License :: OSI Approved :: MIT License
Classifier: Programming Language :: Python :: 3
Classifier: Programming Language :: Python :: 3.8
Classifier: Programming Language :: Python :: 3.9
Classifier: Programming Language :: Python :: 3.10
Classifier: Programming Language :: Python :: 3.11
Classifier: Topic :: Security
Classifier: Topic :: Software Development :: Testing
Requires-Python: >=3.8
Requires-Dist: click>=8.1
Requires-Dist: rich>=13.0
Requires-Dist: requests>=2.31.0
Requires-Dist: python-dotenv>=1.0.0
Provides-Extra: dev
Requires-Dist: pytest>=7.0; extra == "dev"
Requires-Dist: black>=23.0; extra == "dev"
Requires-Dist: mypy>=1.0; extra == "dev"
Requires-Dist: pre-commit>=3.0; extra == "dev"
Requires-Dist: pytest-cov>=4.0; extra == "dev"
Provides-Extra: html
Requires-Dist: lxml>=4.9.0; extra == "html"
Provides-Extra: ai
Requires-Dist: httpx; extra == "ai"
Requires-Dist: google-generativeai; extra == "ai"
Requires-Dist: openai; extra == "ai"
Provides-Extra: crypto
Requires-Dist: mnemonic; extra == "crypto"
Requires-Dist: eth-account; extra == "crypto"
Provides-Extra: scraper
Requires-Dist: aiohttp; extra == "scraper"
Requires-Dist: beautifulsoup4; extra == "scraper"
Requires-Dist: requests; extra == "scraper"
Provides-Extra: tor
Requires-Dist: pysocks; extra == "tor"
Requires-Dist: stem; extra == "tor"
Provides-Extra: all
Requires-Dist: httpx; extra == "all"
Requires-Dist: google-generativeai; extra == "all"
Requires-Dist: openai; extra == "all"
Requires-Dist: mnemonic; extra == "all"
Requires-Dist: eth-account; extra == "all"
Requires-Dist: aiohttp; extra == "all"
Requires-Dist: beautifulsoup4; extra == "all"
Requires-Dist: requests; extra == "all"
Requires-Dist: pysocks; extra == "all"
Requires-Dist: stem; extra == "all"
Provides-Extra: termux
Requires-Dist: requests>=2.31.0; extra == "termux"
Requires-Dist: rich>=13.0; extra == "termux"
Dynamic: author
Dynamic: home-page
Dynamic: requires-python
